memberaudit/__init__.py
memberaudit/admin.py
memberaudit/app_settings.py
memberaudit/apps.py
memberaudit/auth_hooks.py
memberaudit/checks.py
memberaudit/constants.py
memberaudit/decorators.py
memberaudit/errors.py
memberaudit/forms.py
memberaudit/helpers.py
memberaudit/providers.py
memberaudit/signals.py
memberaudit/tasks.py
memberaudit/urls.py
memberaudit/utils.py
memberaudit/core/__init__.py
memberaudit/core/data_exporters.py
memberaudit/core/eft_parser.py
memberaudit/core/esi_status.py
memberaudit/core/fittings.py
memberaudit/core/player_count.py
memberaudit/core/skill_plans.py
memberaudit/core/skills.py
memberaudit/core/standings.py
memberaudit/core/xml_converter.py
memberaudit/locale/django.pot
memberaudit/locale/de/LC_MESSAGES/django.mo
memberaudit/locale/de/LC_MESSAGES/django.po
memberaudit/locale/en/LC_MESSAGES/django.mo
memberaudit/locale/en/LC_MESSAGES/django.po
memberaudit/locale/es/LC_MESSAGES/django.mo
memberaudit/locale/es/LC_MESSAGES/django.po
memberaudit/locale/fr_FR/LC_MESSAGES/django.mo
memberaudit/locale/fr_FR/LC_MESSAGES/django.po
memberaudit/locale/it_IT/LC_MESSAGES/django.mo
memberaudit/locale/it_IT/LC_MESSAGES/django.po
memberaudit/locale/ja/LC_MESSAGES/django.mo
memberaudit/locale/ja/LC_MESSAGES/django.po
memberaudit/locale/ko_KR/LC_MESSAGES/django.mo
memberaudit/locale/ko_KR/LC_MESSAGES/django.po
memberaudit/locale/ru/LC_MESSAGES/django.mo
memberaudit/locale/ru/LC_MESSAGES/django.po
memberaudit/locale/uk/LC_MESSAGES/django.mo
memberaudit/locale/uk/LC_MESSAGES/django.po
memberaudit/locale/zh_Hans/LC_MESSAGES/django.mo
memberaudit/locale/zh_Hans/LC_MESSAGES/django.po
memberaudit/management/commands/__init__.py
memberaudit/management/commands/_helpers.py
memberaudit/management/commands/memberaudit_data_export.py
memberaudit/management/commands/memberaudit_fix_eve_entities.py
memberaudit/management/commands/memberaudit_fix_locations.py
memberaudit/management/commands/memberaudit_load_eve.py
aa_memberaudit-4.2.0.dist-info/licenses/LICENSE
aa_memberaudit-4.2.0.dist-info/WHEEL
aa_memberaudit-4.2.0.dist-info/METADATA
aa_memberaudit-4.2.0.dist-info/RECORD
