Metadata-Version: 2.4
Name: aa-memberaudit
Version: 4.2.0
Summary: An Alliance Auth app that provides full access to Eve characters
Keywords: allianceauth,eveonline,memberaudit
Author-email: Erik Kalkoken <kalkoken87@gmail.com>, Peter Pfeufer <develop@ppfeufer.de>, Rebecca Murphy <rebecca@rcmurphy.me>
Requires-Python: >=3.8
Classifier: Environment :: Web Environment
Classifier: Framework :: Django
Classifier: Framework :: Django :: 4.2
Classifier: Intended Audience :: Developers
Classifier: License :: OSI Approved :: MIT License
Classifier: Operating System :: OS Independent
Classifier: Programming Language :: Python
Classifier: Programming Language :: Python :: 3.8
Classifier: Programming Language :: Python :: 3.9
Classifier: Programming Language :: Python :: 3.10
Classifier: Programming Language :: Python :: 3.11
Classifier: Programming Language :: Python :: 3.12
Classifier: Topic :: Internet :: WWW/HTTP
Classifier: Topic :: Internet :: WWW/HTTP :: Dynamic Content
License-File: LICENSE
Requires-Dist: allianceauth-app-utils>=1.30
Requires-Dist: allianceauth>=4,<5
Requires-Dist: django-esi>=7
Requires-Dist: bleach
Requires-Dist: dj-datatables-view
Requires-Dist: django-eveuniverse>=1.6
Requires-Dist: humanize>=4.7.0
Requires-Dist: unidecode
Requires-Dist: tqdm>=4.66
Project-URL: Changelog, https://gitlab.com/ErikKalkoken/aa-memberaudit/-/blob/master/CHANGELOG.md
Project-URL: Documentation, https://aa-memberaudit.readthedocs.io/en/latest/
Project-URL: Homepage, https://gitlab.com/ErikKalkoken/aa-memberaudit
Project-URL: Source, https://gitlab.com/ErikKalkoken/aa-memberaudit
Project-URL: Tracker, https://gitlab.com/ErikKalkoken/aa-memberaudit/-/issues
